LICENSE.txt
MANIFEST.in
Makefile
README.rst
requirements.txt
setup.py
version.py
pybtracker/__init__.py
pybtracker/client.py
pybtracker/server.py
pybtracker.egg-info/PKG-INFO
pybtracker.egg-info/SOURCES.txt
pybtracker.egg-info/dependency_links.txt
pybtracker.egg-info/entry_points.txt
pybtracker.egg-info/requires.txt
pybtracker.egg-info/top_level.txt