Metadata-Version: 1.1
Name: pybtracker
Version: 0.1.2
Summary: Simple asyncio-based UDP BitTorrent tracker, with a simple client.
Home-page: https://github.com/elektito/pybtracker
Author: Mostafa Razavi
Author-email: mostafa@sepent.com
License: MIT
Download-URL: https://github.com/elektito/pybtracker/tarball/0.1.2
Keywords: bittorrent,torrent,tracker,asyncio,udp
Platform: UNKNOWN
Classifier: Programming Language :: Python :: 3
